aws_cdk/aws_pipes_targets_alpha/__init__.py
aws_cdk/aws_pipes_targets_alpha/py.typed
aws_cdk/aws_pipes_targets_alpha/_jsii/__init__.py
aws_cdk/aws_pipes_targets_alpha/_jsii/aws-pipes-targets-alpha@2.236.0-alpha.0.jsii.tgz
aws_cdk_aws_pipes_targets_alpha-2.236.0a0.dist-info/LICENSE
aws_cdk_aws_pipes_targets_alpha-2.236.0a0.dist-info/METADATA
aws_cdk_aws_pipes_targets_alpha-2.236.0a0.dist-info/NOTICE
aws_cdk_aws_pipes_targets_alpha-2.236.0a0.dist-info/WHEEL
aws_cdk_aws_pipes_targets_alpha-2.236.0a0.dist-info/top_level.txt
aws_cdk_aws_pipes_targets_alpha-2.236.0a0.dist-info/RECORD
